cmlibs/__init__.py
cmlibs/merger/__init__.py
cmlibs/merger/datapoints.py
cmlibs/merger/errors.py
cmlibs/merger/points.py
cmlibs_merger-0.4.0.dist-info/licenses/LICENSE
cmlibs_merger-0.4.0.dist-info/METADATA
cmlibs_merger-0.4.0.dist-info/WHEEL
cmlibs_merger-0.4.0.dist-info/top_level.txt
cmlibs_merger-0.4.0.dist-info/RECORD
